{"title":"Cyberdelia","code":"21006","overTime":[{"cardtitle":"Cyberdelia","sidecode":"runner","faction":"shaper","cardpacktitle":"Sovereign Sight","dpnumber":1,"cyclenumber":21,"indecks":8,"intopdecks":4,"deckfraction":0.09090909361839294,"topdeckfraction":0.0784313753247261},{"cardtitle":"Cyberdelia","sidecode":"runner","faction":"shaper","cardpacktitle":"Down the White Nile","dpnumber":2,"cyclenumber":21,"indecks":9,"intopdecks":5,"deckfraction":0.04891304299235344,"topdeckfraction":0.049504950642585754},{"cardtitle":"Cyberdelia","sidecode":"runner","faction":"shaper","cardpacktitle":"Council of the Crest","dpnumber":3,"cyclenumber":21,"indecks":14,"intopdecks":4,"deckfraction":0.08974359184503555,"topdeckfraction":0.0533333346247673},{"cardtitle":"Cyberdelia","sidecode":"runner","faction":"shaper","cardpacktitle":"The Devil and the Dragon","dpnumber":4,"cyclenumber":21,"indecks":1,"intopdecks":0,"deckfraction":0.0833333358168602,"topdeckfraction":0.0},{"cardtitle":"Cyberdelia","sidecode":"runner","faction":"shaper","cardpacktitle":"Whispers in Nalubaale","dpnumber":5,"cyclenumber":21,"indecks":5,"intopdecks":2,"deckfraction":0.036231882870197296,"topdeckfraction":0.032786883413791656},{"cardtitle":"Cyberdelia","sidecode":"runner","faction":"shaper","cardpacktitle":"Kampala Ascendent","dpnumber":6,"cyclenumber":21,"indecks":4,"intopdecks":1,"deckfraction":0.03200000151991844,"topdeckfraction":0.016393441706895828},{"cardtitle":"Cyberdelia","sidecode":"runner","faction":"shaper","cardpacktitle":"Reign and Reverie","dpnumber":1,"cyclenumber":22,"indecks":6,"intopdecks":4,"deckfraction":0.021052632480859756,"topdeckfraction":0.028368793427944183},{"cardtitle":"Cyberdelia","sidecode":"runner","faction":"shaper","cardpacktitle":"R&R MWL 2.2","dpnumber":2,"cyclenumber":22,"indecks":7,"intopdecks":5,"deckfraction":0.03465346619486809,"topdeckfraction":0.04716981202363968},{"cardtitle":"Cyberdelia","sidecode":"runner","faction":"shaper","cardpacktitle":"Magnum Opus","dpnumber":1,"cyclenumber":23,"indecks":7,"intopdecks":1,"deckfraction":0.0560000017285347,"topdeckfraction":0.022727273404598236},{"cardtitle":"Cyberdelia","sidecode":"runner","faction":"shaper","cardpacktitle":"System Core 2019","dpnumber":1,"cyclenumber":25,"indecks":14,"intopdecks":3,"deckfraction":0.05263157933950424,"topdeckfraction":0.02459016442298889},{"cardtitle":"Cyberdelia","sidecode":"runner","faction":"shaper","cardpacktitle":"Downfall","dpnumber":1,"cyclenumber":26,"indecks":7,"intopdecks":3,"deckfraction":0.04268292710185051,"topdeckfraction":0.04054053872823715}],"top":[{"cardtitle":"Hayley Kaplan: Universal Scholar","sidecode":"runner","faction":"shaper","cardpacktitle":"Breaker Bay","dpnumber":2,"cyclenumber":8,"indecks":7,"intopdecks":-1,"deckfraction":0.12068965286016464,"topdeckfraction":-1.0},{"cardtitle":"Kabonesa Wu: Netspace Thrillseeker","sidecode":"runner","faction":"shaper","cardpacktitle":"Down the White Nile","dpnumber":2,"cyclenumber":21,"indecks":5,"intopdecks":-1,"deckfraction":0.2631579041481018,"topdeckfraction":-1.0},{"cardtitle":"Ele \"Smoke\" Scovak: Cynosure of the Net","sidecode":"runner","faction":"shaper","cardpacktitle":"Intervention","dpnumber":4,"cyclenumber":11,"indecks":5,"intopdecks":-1,"deckfraction":0.1666666716337204,"topdeckfraction":-1.0},{"cardtitle":"Rielle \"Kit\" Peddler: Transhuman","sidecode":"runner","faction":"shaper","cardpacktitle":"System Core 2019","dpnumber":1,"cyclenumber":25,"indecks":4,"intopdecks":-1,"deckfraction":0.5714285969734192,"topdeckfraction":-1.0},{"cardtitle":"Jesminder Sareen: Girl Behind the Curtain","sidecode":"runner","faction":"shaper","cardpacktitle":"Kala Ghoda","dpnumber":1,"cyclenumber":10,"indecks":4,"intopdecks":-1,"deckfraction":0.1666666716337204,"topdeckfraction":-1.0},{"cardtitle":"The Professor: Keeper of Knowledge","sidecode":"runner","faction":"shaper","cardpacktitle":"Creation and Control","dpnumber":1,"cyclenumber":3,"indecks":1,"intopdecks":-1,"deckfraction":1.0,"topdeckfraction":-1.0},{"cardtitle":"Ayla \"Bios\" Rahim: Simulant Specialist","sidecode":"runner","faction":"shaper","cardpacktitle":"Terminal Directive","dpnumber":1,"cyclenumber":13,"indecks":1,"intopdecks":-1,"deckfraction":0.3333333432674408,"topdeckfraction":-1.0},{"cardtitle":"Akiko Nisei: Head Case","sidecode":"runner","faction":"shaper","cardpacktitle":"Reign and Reverie","dpnumber":1,"cyclenumber":22,"indecks":1,"intopdecks":-1,"deckfraction":0.5,"topdeckfraction":-1.0}],"combos":[{"title":"Self-modifying Code","pack":"Creation and Control","faction":"shaper","score":43},{"title":"Beth Kilrain-Chang","pack":"Blood Money","faction":"shaper","score":34},{"title":"Takobi","pack":"Down the White Nile","faction":"shaper","score":31},{"title":"Misdirection","pack":"Martial Law","faction":"shaper","score":29},{"title":"Feedback Filter","pack":"Creation and Control","faction":"shaper","score":28},{"title":"Na'Not'K","pack":"Free Mars","faction":"shaper","score":25},{"title":"Mind's Eye","pack":"Reign and Reverie","faction":"shaper","score":25},{"title":"Modded","pack":"System Core 2019","faction":"shaper","score":20},{"title":"Magnum Opus","pack":"Revised Core Set","faction":"shaper","score":19},{"title":"Clot","pack":"The Valley","faction":"anarch","score":16}],"decks":[{"count":7,"dpnumber":1,"cyclenumber":26,"dptitle":"Downfall","deckLinks":["<a href=\"https://netrunnerdb.com/en/decklist/55051\" rel=\"nofollow\" target=\"_blank\">Smoking Gun</a> by <em>Hipcat</em> (#5 / 6 at Dork Den Store Championship, Mankato, MN)","<a href=\"https://netrunnerdb.com/en/decklist/55248\" rel=\"nofollow\" target=\"_blank\">Wu'd by the Stars. 2-1 Lexington SC, w/ first-round bye</a> by <em>Janktivist</em> (#1 / 9 at Lexington, KY Store Championship)","<a href=\"https://netrunnerdb.com/en/decklist/54880\" rel=\"nofollow\" target=\"_blank\">surfer Wu</a> by <em>Daine</em> (#2 / 9 at Milwaukee Nisei Store Championship)","<a href=\"https://netrunnerdb.com/en/decklist/55207\" rel=\"nofollow\" target=\"_blank\">Gauntlet Rezeki Rejigger</a> by <em>profDEADPOOL</em> (#8 / 15 at Store Championship 2019 at Black Diamond Games)","<a href=\"https://netrunnerdb.com/en/decklist/55189\" rel=\"nofollow\" target=\"_blank\">I Spy with My Mind's Eye... 10th place Sydney 2019 Store Cha</a> by <em>Icedman</em> (#10 / 15 at Sydney Nisei Store Champs)","<a href=\"https://netrunnerdb.com/en/decklist/55305\" rel=\"nofollow\" target=\"_blank\">Pursuing JesMinder's Eye</a> by <em>hnautsch</em> (#4 / 5 at Linköping Netrunner Store Championship 2019)","<a href=\"https://netrunnerdb.com/en/decklist/55051\" rel=\"nofollow\" target=\"_blank\">Smoking Gun</a> by <em>Hipcat</em> (#5 / 6 at Dork Den Store Championship, Mankato, MN)"]},{"count":14,"dpnumber":1,"cyclenumber":25,"dptitle":"System Core 2019","deckLinks":["<a href=\"https://netrunnerdb.com/en/decklist/54284\" rel=\"nofollow\" target=\"_blank\">Kickstarter Hayley - Interdicted</a> by <em>Bl4nk3t</em> (#3 / 35 at Double Play Community Tournament Berlin (2 days))","<a href=\"https://netrunnerdb.com/en/decklist/53976\" rel=\"nofollow\" target=\"_blank\">B-Comm Hayley 5th place</a> by <em>ayyyliens</em> (#5 / 36 at Barcelona Community Event - B-Com 2)","<a href=\"https://netrunnerdb.com/en/decklist/54750\" rel=\"nofollow\" target=\"_blank\">Pajammeez Jes +</a> by <em>Zerothmaxima</em> (#1 / 7 at Calgary Netrunner Q3 2018 GNK)","<a href=\"https://netrunnerdb.com/en/decklist/54556\" rel=\"nofollow\" target=\"_blank\">KaboNISEI 1.10 — Paris GNK ed.</a> by <em>metamatik</em> (#4 / 13 at Paris NISEI Q1 2019 GNK)","<a href=\"https://netrunnerdb.com/en/decklist/53800\" rel=\"nofollow\" target=\"_blank\">Kickstarter Hayley (Nisei GNK)</a> by <em>CodeMarvelous</em> (#2 / 6 at Prague January GNK)","<a href=\"https://netrunnerdb.com/en/decklist/53869\" rel=\"nofollow\" target=\"_blank\">Hayley</a> by <em>morgon82</em> (#3 / 9 at First NISEI GNK 2019 in LUBUSKIE)","<a href=\"https://netrunnerdb.com/en/decklist/54790\" rel=\"nofollow\" target=\"_blank\">Engolo kit</a> by <em>LSTM</em> (#4 / 9 at The Portland Game Store 2019 Store Championship)","<a href=\"https://netrunnerdb.com/en/decklist/54204\" rel=\"nofollow\" target=\"_blank\">Kit</a> by <em>NinjaMike</em> (#6 / 12 at Rhinio Nisei Q1 GNK)","<a href=\"https://netrunnerdb.com/en/decklist/54115\" rel=\"nofollow\" target=\"_blank\">Kraut Hayley 1.0</a> by <em>5N00P1</em> (#6 / 8 at Berlin 2nd January GNK)","<a href=\"https://netrunnerdb.com/en/decklist/53976\" rel=\"nofollow\" target=\"_blank\">B-Comm Hayley 5th place</a> by <em>ayyyliens</em> (#5 / 36 at Barcelona Community Event - B-Com 2)","..."]},{"count":7,"dpnumber":1,"cyclenumber":23,"dptitle":"Magnum Opus","deckLinks":["<a href=\"https://netrunnerdb.com/en/decklist/53429\" rel=\"nofollow\" target=\"_blank\">Oh S#*t. It's Kit. (12th/48 at Laser Runner)</a> by <em>Pommes</em> (#12 / 48 at LaserRunner)","<a href=\"https://netrunnerdb.com/en/decklist/52871\" rel=\"nofollow\" target=\"_blank\">Mindshop Smoke (4-2-5, #9 & #14 Euregio Weekend)</a> by <em>lostgeek</em> (#9 / 27 at Hiveworld October GNK / Euregio-Warmup)","<a href=\"https://netrunnerdb.com/en/decklist/52871\" rel=\"nofollow\" target=\"_blank\">Mindshop Smoke (4-2-5, #9 & #14 Euregio Weekend)</a> by <em>lostgeek</em> (#9 / 27 at Hiveworld October GNK / Euregio-Warmup)","<a href=\"https://netrunnerdb.com/en/decklist/52836\" rel=\"nofollow\" target=\"_blank\">Karlshamn Akiko </a> by <em>hnautsch</em> (#7 / 12 at Netrunner tournament)","<a href=\"https://netrunnerdb.com/en/decklist/53084\" rel=\"nofollow\" target=\"_blank\">Good gaaaaames, everyone! (6th at Diversified Portfolio)</a> by <em>Cpt_nice</em> (#6 / 10 at Dutch Nationals: Diversified Portfolio side event)","<a href=\"https://netrunnerdb.com/en/decklist/52871\" rel=\"nofollow\" target=\"_blank\">Mindshop Smoke (4-2-5, #9 & #14 Euregio Weekend)</a> by <em>lostgeek</em> (#9 / 27 at Hiveworld October GNK / Euregio-Warmup)","<a href=\"https://netrunnerdb.com/en/decklist/53022\" rel=\"nofollow\" target=\"_blank\">Flower Power</a> by <em>Random Word</em> (#14 / 15 at Meat Damage, a farewell to netrunner)"]},{"count":7,"dpnumber":2,"cyclenumber":22,"dptitle":"R&R MWL 2.2","deckLinks":["<a href=\"https://netrunnerdb.com/en/decklist/52472\" rel=\"nofollow\" target=\"_blank\">Lean and Mean: Stealth Kabonesa (29th @ Worlds)</a> by <em>allofthemarbles</em> (#29 / 403 at Magnum Opus (Worlds 2018))","<a href=\"https://netrunnerdb.com/en/decklist/53418\" rel=\"nofollow\" target=\"_blank\">Laser Wu (1st Gent GNK, 9th King of Lasers)</a> by <em>ayyyliens</em> (#1 / 8 at Netrunner Legacy #2)","<a href=\"https://netrunnerdb.com/en/decklist/52303\" rel=\"nofollow\" target=\"_blank\">90's Kit</a> by <em>Roppa</em> (#8 / 45 at Netrunner Nordic Championship 2018)","<a href=\"https://netrunnerdb.com/en/decklist/52303\" rel=\"nofollow\" target=\"_blank\">90's Kit</a> by <em>Roppa</em> (#8 / 45 at Netrunner Nordic Championship 2018)","<a href=\"https://netrunnerdb.com/en/decklist/52766\" rel=\"nofollow\" target=\"_blank\">Χάιπερ Λάιτ Σμόουκ (2nd Place Greek National</a> by <em>Kelfecil</em> (#2 / 10 at Greek Nationals 2018)","<a href=\"https://netrunnerdb.com/en/decklist/52441\" rel=\"nofollow\" target=\"_blank\">Mindshop Smoke [25th at German Nationals 4-3]</a> by <em>lostgeek</em> (#25 / 94 at German Nationals 2018 Main Event)","<a href=\"https://netrunnerdb.com/en/decklist/52480\" rel=\"nofollow\" target=\"_blank\">WuBegone - Do The Shaper Dance (6-1 in Swiss, Worlds)</a> by <em>Aesynil</em> (#8 / 10 at Hiveworld September GNK)"]},{"count":6,"dpnumber":1,"cyclenumber":22,"dptitle":"Reign and Reverie","deckLinks":["<a href=\"https://netrunnerdb.com/en/decklist/51769\" rel=\"nofollow\" target=\"_blank\">Software Key V1.3</a> by <em>CrashT</em> (#1 / 14 at RanEnc Monthly Netrunner 5 - TO's Birthday Bash)","<a href=\"https://netrunnerdb.com/en/decklist/51537\" rel=\"nofollow\" target=\"_blank\">QWOPerado — pretty good, NorCal Regionals</a> by <em>aleph_c</em> (#6 / 36 at Game Kastle Mountain View Regional)","<a href=\"https://netrunnerdb.com/en/decklist/51892\" rel=\"nofollow\" target=\"_blank\">Brave Enough For Remixes</a> by <em>Espatier</em> (#9 / 30 at Sheffield Regionals)","<a href=\"https://netrunnerdb.com/en/decklist/51801\" rel=\"nofollow\" target=\"_blank\">Software Key V1.3.1</a> by <em>SpaceHonk</em> (#3 / 10 at Hiveworld August GNK)","<a href=\"https://netrunnerdb.com/en/decklist/51578\" rel=\"nofollow\" target=\"_blank\">Jesminder - Surf And Turf 1.3</a> by <em>saracenus</em> (#4 / 9 at TPGS - 2018 Season 2 Critical Run Tournament)","<a href=\"https://netrunnerdb.com/en/decklist/49299\" rel=\"nofollow\" target=\"_blank\">Swipsy-Swapsies (3-1 Kzoo SC)</a> by <em>PureFlight</em> (#20 / 33 at Regionals Stockholm, Sweden 2018)"]},{"count":4,"dpnumber":6,"cyclenumber":21,"dptitle":"Kampala Ascendent","deckLinks":["<a href=\"https://netrunnerdb.com/en/decklist/50949\" rel=\"nofollow\" target=\"_blank\">Χάιπερ Λάιτ Σμόουκ 0.3</a> by <em>Kelfecil</em> (#2 / 7 at Thessaloniki Grim Running)","<a href=\"https://netrunnerdb.com/en/decklist/50977\" rel=\"nofollow\" target=\"_blank\">A Nostalgic Trip Up The Beanstalk (2-2 at a GNK)</a> by <em>Sanjay</em> (#5 / 13 at A Pleasant Netrunner GNK)","<a href=\"https://netrunnerdb.com/en/decklist/51002\" rel=\"nofollow\" target=\"_blank\">Jesminder - Surf And Turf (45th at US Nationals)</a> by <em>saracenus</em> (#45 / 61 at 2018 US Nationals)","<a href=\"https://netrunnerdb.com/en/decklist/51466\" rel=\"nofollow\" target=\"_blank\">Cache Refresh Monolith Ayla</a> by <em>Necro</em> (#39 / 50 at Stimhack Online Cache Refresh 6 (SOCR 6))"]},{"count":5,"dpnumber":5,"cyclenumber":21,"dptitle":"Whispers in Nalubaale","deckLinks":["<a href=\"https://netrunnerdb.com/en/decklist/50172\" rel=\"nofollow\" target=\"_blank\">I don't know, Jackpot?</a> by <em>aleph_c</em> (#2 / 12 at Eude May)","<a href=\"https://netrunnerdb.com/en/decklist/50275\" rel=\"nofollow\" target=\"_blank\">Wu you gonna call? 1.1 -- 2nd at Prague GNK</a> by <em>DTonius</em> (#2 / 7 at Turnaj Praha Android: Netrunner 12.5.2018)","<a href=\"https://netrunnerdb.com/en/decklist/50574\" rel=\"nofollow\" target=\"_blank\">Wu Magic v0</a> by <em>Jose-san</em> (#83 / 244 at FFG European Championships 2018)","<a href=\"https://netrunnerdb.com/en/decklist/50245\" rel=\"nofollow\" target=\"_blank\">Surfer Lock</a> by <em>aDumbBrick</em> (#3 / 5 at Starlit Citadel May GNK)","<a href=\"https://netrunnerdb.com/en/decklist/50352\" rel=\"nofollow\" target=\"_blank\">Suicide Jesminder 19/05/18</a> by <em>ayyyliens</em> (#9 / 10 at Antwerpen Seasonal Kit)"]},{"count":1,"dpnumber":4,"cyclenumber":21,"dptitle":"The Devil and the Dragon","deckLinks":["<a href=\"https://netrunnerdb.com/en/decklist/48967\" rel=\"nofollow\" target=\"_blank\">Wubicon - Undefeated Colorado SC - 2nd Place</a> by <em>mathandlove</em> (#4 / 8 at Rockford GNK - April 2018)"]},{"count":14,"dpnumber":3,"cyclenumber":21,"dptitle":"Council of the Crest","deckLinks":["<a href=\"https://netrunnerdb.com/en/decklist/49416\" rel=\"nofollow\" target=\"_blank\">Memories of the Zoo - 1st at Preston (DnD) SC</a> by <em>mcg</em> (#1 / 16 at Dice & Donuts Store Championship)","<a href=\"https://netrunnerdb.com/en/decklist/49103\" rel=\"nofollow\" target=\"_blank\">Memory Lane Hayley - KoS & 2nd @ Stockport SC</a> by <em>mcg</em> (#2 / 12 at Android: Netrunner Store Champs)","<a href=\"https://netrunnerdb.com/en/decklist/49588\" rel=\"nofollow\" target=\"_blank\">Χάιπερ Λάιτ Σμόουκ 0.2</a> by <em>Kelfecil</em> (#3 / 15 at Store Champs | Tabletop Kingdom (Den Haag))","<a href=\"https://netrunnerdb.com/en/decklist/48967\" rel=\"nofollow\" target=\"_blank\">Wubicon - Undefeated Colorado SC - 2nd Place</a> by <em>mathandlove</em> (#4 / 8 at Rockford GNK - April 2018)","<a href=\"https://netrunnerdb.com/en/decklist/49299\" rel=\"nofollow\" target=\"_blank\">Swipsy-Swapsies (3-1 Kzoo SC)</a> by <em>PureFlight</em> (#20 / 33 at Regionals Stockholm, Sweden 2018)","<a href=\"https://netrunnerdb.com/en/decklist/49304\" rel=\"nofollow\" target=\"_blank\">L.A.Y.L.A.</a> by <em>cwoac</em> (#6 / 12 at Netrunner - Incom Gaming Store Championship)","<a href=\"https://netrunnerdb.com/en/decklist/49447\" rel=\"nofollow\" target=\"_blank\">2XX1: A Runner Odyssey ProCo</a> by <em>Ino209</em> (#16 / 29 at ANRPC Charity Event 2)","<a href=\"https://netrunnerdb.com/en/decklist/49397\" rel=\"nofollow\" target=\"_blank\">Efficient Ayla</a> by <em>HiddenAway</em> (#12 / 16 at Dice & Donuts Store Championship)","<a href=\"https://netrunnerdb.com/en/decklist/49512\" rel=\"nofollow\" target=\"_blank\">Efficient Ayla (Preston Harlequins)</a> by <em>HiddenAway</em> (#14 / 18 at Harlequins Preston Netrunner Store Championship)","<a href=\"https://netrunnerdb.com/en/decklist/49529\" rel=\"nofollow\" target=\"_blank\">Wu you gonna call? 1.0</a> by <em>DTonius</em> (#11 / 13 at Bratislava Store Champs - March 2018)","..."]},{"count":9,"dpnumber":2,"cyclenumber":21,"dptitle":"Down the White Nile","deckLinks":["<a href=\"https://netrunnerdb.com/en/decklist/49284\" rel=\"nofollow\" target=\"_blank\">Moscow Trickster (1st Moscow SC, 5-1)</a> by <em>woland</em> (#1 / 17 at Moscow Store Championship 2018)","<a href=\"https://netrunnerdb.com/en/decklist/48658\" rel=\"nofollow\" target=\"_blank\">O-RNG Crush - 2nd Place @ Games and Stuff SC</a> by <em>CodeMarvelous</em> (#2 / 21 at Games and Stuff Store Championship)","<a href=\"https://netrunnerdb.com/en/decklist/47925\" rel=\"nofollow\" target=\"_blank\">Dance Dance Mopus [1st Place Store Champs]</a> by <em>enkoder</em> (#1 / 10 at Store Championship: Lorien)","<a href=\"https://netrunnerdb.com/en/decklist/48967\" rel=\"nofollow\" target=\"_blank\">Wubicon - Undefeated Colorado SC - 2nd Place</a> by <em>mathandlove</em> (#4 / 8 at Rockford GNK - April 2018)","<a href=\"https://netrunnerdb.com/en/decklist/48347\" rel=\"nofollow\" target=\"_blank\">a shaper deck</a> by <em>themeanlady</em> (#2 / 16 at Gamers Haven Store Championship)","<a href=\"https://netrunnerdb.com/en/decklist/48946\" rel=\"nofollow\" target=\"_blank\">Wuligion - 2017 Store Championship 2018-02-25 (2W 2L)</a> by <em>Ozasuke</em> (#7 / 10 at Rainy Day ANR Store Championship)","<a href=\"https://netrunnerdb.com/en/decklist/48765\" rel=\"nofollow\" target=\"_blank\">Adaptation of THE ART OF FOLDING 2.0</a> by <em>HakanCarlstrom</em> (#7 / 10 at Store Championships @ FirstPlayer, Varberg, Sweden)","<a href=\"https://netrunnerdb.com/en/decklist/49066\" rel=\"nofollow\" target=\"_blank\">Adaptation of THE ART OF FOLDING 2.0</a> by <em>HakanCarlstrom</em> (#10 / 12 at Android Netrunner Store Championship Halmstad)","<a href=\"https://netrunnerdb.com/en/decklist/48887\" rel=\"nofollow\" target=\"_blank\">There is no Spoon 2.03</a> by <em>haywire</em> (#8 / 8 at Highlander Games Bremen - GNK / Seasonal Tournament)"]},{"count":8,"dpnumber":1,"cyclenumber":21,"dptitle":"Sovereign Sight","deckLinks":["<a href=\"https://netrunnerdb.com/en/decklist/48138\" rel=\"nofollow\" target=\"_blank\">Dance Dance Mopus [1st Place Store Champs]</a> by <em>Pedantic</em> (#1 / 18 at 2018 Android: Netrunner Store Championship)","<a href=\"https://netrunnerdb.com/en/decklist/47925\" rel=\"nofollow\" target=\"_blank\">Dance Dance Mopus [1st Place Store Champs]</a> by <em>enkoder</em> (#1 / 10 at Store Championship: Lorien)","<a href=\"https://netrunnerdb.com/en/decklist/47683\" rel=\"nofollow\" target=\"_blank\">CyberDevil 2.0</a> by <em>Joseki</em> (#3 / 16 at Gamescape SF Store Championship)","<a href=\"https://netrunnerdb.com/en/decklist/48251\" rel=\"nofollow\" target=\"_blank\">Kit - 2nd place @ IW Heroes SC</a> by <em>ScrappySPJ</em> (#2 / 8 at Netrunner 2018 Store Championship)","<a href=\"https://netrunnerdb.com/en/decklist/47505\" rel=\"nofollow\" target=\"_blank\">CyberDevil</a> by <em>Joseki</em> (#1 / 3 at Eudo 3rd December GNK)","<a href=\"https://netrunnerdb.com/en/decklist/47975\" rel=\"nofollow\" target=\"_blank\">Inverse Kit</a> by <em>wigglestick</em> (#4 / 8 at Spielbound GNK)","<a href=\"https://netrunnerdb.com/en/decklist/48213\" rel=\"nofollow\" target=\"_blank\">Dance Dance Mopus (Modded)</a> by <em>HiddenAway</em> (#28 / 30 at Fan Boy Three - Manchester Store Championship)","<a href=\"https://netrunnerdb.com/en/decklist/48539\" rel=\"nofollow\" target=\"_blank\">Maxus Ayla 0.8</a> by <em>5N00P1</em> (#13 / 13 at Store Championship Spieleburg Kassel)"]}]}