{"title":"Peeping Tom","code":"22045","overTime":[{"cardtitle":"Peeping Tom","sidecode":"corp","faction":"nbn","cardpacktitle":"Reign and Reverie","dpnumber":1,"cyclenumber":22,"indecks":0,"intopdecks":0,"deckfraction":0.0,"topdeckfraction":0.0},{"cardtitle":"Peeping Tom","sidecode":"corp","faction":"nbn","cardpacktitle":"R&R MWL 2.2","dpnumber":2,"cyclenumber":22,"indecks":1,"intopdecks":1,"deckfraction":0.005050505045801401,"topdeckfraction":0.009523809887468815},{"cardtitle":"Peeping Tom","sidecode":"corp","faction":"nbn","cardpacktitle":"Magnum Opus","dpnumber":1,"cyclenumber":23,"indecks":2,"intopdecks":0,"deckfraction":0.01600000075995922,"topdeckfraction":0.0},{"cardtitle":"Peeping Tom","sidecode":"corp","faction":"nbn","cardpacktitle":"System Core 2019","dpnumber":1,"cyclenumber":25,"indecks":4,"intopdecks":3,"deckfraction":0.015325670130550861,"topdeckfraction":0.02500000037252903},{"cardtitle":"Peeping Tom","sidecode":"corp","faction":"nbn","cardpacktitle":"Downfall","dpnumber":1,"cyclenumber":26,"indecks":2,"intopdecks":1,"deckfraction":0.007462686393409967,"topdeckfraction":0.008333333767950535},{"cardtitle":"Peeping Tom","sidecode":"corp","faction":"nbn","cardpacktitle":"Downfall MWL 3.2","dpnumber":2,"cyclenumber":26,"indecks":0,"intopdecks":0,"deckfraction":0.0,"topdeckfraction":0.0},{"cardtitle":"Peeping Tom","sidecode":"corp","faction":"nbn","cardpacktitle":"Downfall MWL 3.3","dpnumber":3,"cyclenumber":26,"indecks":2,"intopdecks":1,"deckfraction":0.008620689623057842,"topdeckfraction":0.009708737954497337},{"cardtitle":"Peeping Tom","sidecode":"corp","faction":"nbn","cardpacktitle":"Uprising Booster Pack","dpnumber":4,"cyclenumber":26,"indecks":0,"intopdecks":0,"deckfraction":0.0,"topdeckfraction":0.0},{"cardtitle":"Peeping Tom","sidecode":"corp","faction":"nbn","cardpacktitle":"Uprising","dpnumber":5,"cyclenumber":26,"indecks":0,"intopdecks":0,"deckfraction":0.0,"topdeckfraction":0.0}],"top":[{"cardtitle":"Azmari EdTech: Shaping the Future","sidecode":"corp","faction":"nbn","cardpacktitle":"Council of the Crest","dpnumber":3,"cyclenumber":21,"indecks":2,"intopdecks":-1,"deckfraction":0.03448275849223137,"topdeckfraction":-1.0}],"combos":[{"title":"Salem's Hospitality","pack":"Salsette Island","faction":"nbn","score":62},{"title":"Endless EULA","pack":"The Devil and the Dragon","faction":"nbn","score":10},{"title":"Jua","pack":"Down the White Nile","faction":"nbn","score":8},{"title":"Degree Mill","pack":"Council of the Crest","faction":"nbn","score":8},{"title":"Tollbooth","pack":"System Core 2019","faction":"nbn","score":7},{"title":"Slot Machine (old) - mo","pack":"Magnum Opus","faction":"nbn","score":6},{"title":"IP Block","pack":"Martial Law","faction":"nbn","score":5},{"title":"Echo Chamber","pack":"Sovereign Sight","faction":"nbn","score":5},{"title":"Crisium Grid","pack":"System Core 2019","faction":"weyland-consortium","score":4},{"title":"Rashida Jaheem","pack":"The Devil and the Dragon","faction":"neutral","score":3}],"decks":[{"count":0,"dpnumber":5,"cyclenumber":26,"dptitle":"Uprising","deckLinks":[]},{"count":0,"dpnumber":4,"cyclenumber":26,"dptitle":"Uprising Booster Pack","deckLinks":[]},{"count":2,"dpnumber":3,"cyclenumber":26,"dptitle":"Downfall MWL 3.3","deckLinks":["<a href=\"https://netrunnerdb.com/en/decklist/56386\" rel=\"nofollow\" target=\"_blank\">Panic Punitive Azmari</a> by <em>Frost</em> (#7 / 29 at London Regional 2019)","<a href=\"https://netrunnerdb.com/en/decklist/56386\" rel=\"nofollow\" target=\"_blank\">Panic Punitive Azmari</a> by <em>Frost</em> (#8 / 26 at Aldershot Netrunner Regionals 2019)"]},{"count":0,"dpnumber":2,"cyclenumber":26,"dptitle":"Downfall MWL 3.2","deckLinks":[]},{"count":2,"dpnumber":1,"cyclenumber":26,"dptitle":"Downfall","deckLinks":["<a href=\"https://netrunnerdb.com/en/decklist/55344\" rel=\"nofollow\" target=\"_blank\">FAzmari</a> by <em>Zeebag</em> (#3 / 14 at 401 Games Store Championship)","<a href=\"https://netrunnerdb.com/en/decklist/55906\" rel=\"nofollow\" target=\"_blank\">hey can I borrow your 10 cred chips?</a> by <em>Uruz</em> (#11 / 11 at Netrunner Store Championship - Empire Central)"]},{"count":4,"dpnumber":1,"cyclenumber":25,"dptitle":"System Core 2019","deckLinks":["<a href=\"https://netrunnerdb.com/en/decklist/53405\" rel=\"nofollow\" target=\"_blank\">Standard Punitive Azmari</a> by <em>Frost</em> (#1 / 11 at Q3 GNK - SYSTEM CORE + NISEI MWL)","<a href=\"https://netrunnerdb.com/en/decklist/54289\" rel=\"nofollow\" target=\"_blank\">Fly Wishbone (Bristol GNK Winner)</a> by <em>Algebraic</em> (#1 / 7 at Nisei Q1 GNK @ Excelsior Games, Bristol)","<a href=\"https://netrunnerdb.com/en/decklist/54068\" rel=\"nofollow\" target=\"_blank\">Medical Research Fundraiser v2</a> by <em>Sixtyten</em> (#2 / 12 at Netrunner Prize Bonanza GNK)","<a href=\"https://netrunnerdb.com/en/decklist/54068\" rel=\"nofollow\" target=\"_blank\">Medical Research Fundraiser v2</a> by <em>Sixtyten</em> (#4 / 7 at Nisei Q1 GNK @ Excelsior Games, Bristol)"]},{"count":2,"dpnumber":1,"cyclenumber":23,"dptitle":"Magnum Opus","deckLinks":["<a href=\"https://netrunnerdb.com/en/decklist/54068\" rel=\"nofollow\" target=\"_blank\">Medical Research Fundraiser v2</a> by <em>Sixtyten</em> (#12 / 17 at Ciara Maxey Memorial Tournament - Mermaids UK)","<a href=\"https://netrunnerdb.com/en/decklist/54068\" rel=\"nofollow\" target=\"_blank\">Medical Research Fundraiser v2</a> by <em>Sixtyten</em> (#10 / 12 at Charity Gift - President of Servers 2018)"]},{"count":1,"dpnumber":2,"cyclenumber":22,"dptitle":"R&R MWL 2.2","deckLinks":["<a href=\"https://netrunnerdb.com/en/decklist/52134\" rel=\"nofollow\" target=\"_blank\">A Lesson Is Learned But The Stinson Is Irreversible</a> by <em>postinternetsyndrome</em> (#5 / 18 at Örebro Netrunner Regionals)"]},{"count":0,"dpnumber":1,"cyclenumber":22,"dptitle":"Reign and Reverie","deckLinks":[]}]}