{"title":"Paper Tripping","code":"06015","overTime":[{"cardtitle":"Paper Tripping","sidecode":"runner","faction":"criminal","cardpacktitle":"Up and Over","dpnumber":4,"cyclenumber":6,"indecks":0,"intopdecks":0,"deckfraction":0.0,"topdeckfraction":0.0},{"cardtitle":"Paper Tripping","sidecode":"runner","faction":"criminal","cardpacktitle":"All That Remains","dpnumber":5,"cyclenumber":6,"indecks":0,"intopdecks":0,"deckfraction":0.0,"topdeckfraction":0.0},{"cardtitle":"Paper Tripping","sidecode":"runner","faction":"criminal","cardpacktitle":"The Source","dpnumber":6,"cyclenumber":6,"indecks":1,"intopdecks":1,"deckfraction":0.017241379246115685,"topdeckfraction":0.02500000037252903},{"cardtitle":"Paper Tripping","sidecode":"runner","faction":"criminal","cardpacktitle":"Order and Chaos","dpnumber":1,"cyclenumber":7,"indecks":0,"intopdecks":0,"deckfraction":0.0,"topdeckfraction":0.0},{"cardtitle":"Paper Tripping","sidecode":"runner","faction":"criminal","cardpacktitle":"The Valley","dpnumber":1,"cyclenumber":8,"indecks":0,"intopdecks":0,"deckfraction":0.0,"topdeckfraction":0.0},{"cardtitle":"Paper Tripping","sidecode":"runner","faction":"criminal","cardpacktitle":"Breaker Bay","dpnumber":2,"cyclenumber":8,"indecks":0,"intopdecks":0,"deckfraction":0.0,"topdeckfraction":0.0},{"cardtitle":"Paper Tripping","sidecode":"runner","faction":"criminal","cardpacktitle":"Chrome City","dpnumber":3,"cyclenumber":8,"indecks":0,"intopdecks":0,"deckfraction":0.0,"topdeckfraction":0.0},{"cardtitle":"Paper Tripping","sidecode":"runner","faction":"criminal","cardpacktitle":"The Underway","dpnumber":4,"cyclenumber":8,"indecks":0,"intopdecks":0,"deckfraction":0.0,"topdeckfraction":0.0},{"cardtitle":"Paper Tripping","sidecode":"runner","faction":"criminal","cardpacktitle":"Old Hollywood","dpnumber":5,"cyclenumber":8,"indecks":0,"intopdecks":0,"deckfraction":0.0,"topdeckfraction":0.0},{"cardtitle":"Paper Tripping","sidecode":"runner","faction":"criminal","cardpacktitle":"The Universe of Tomorrow","dpnumber":6,"cyclenumber":8,"indecks":0,"intopdecks":0,"deckfraction":0.0,"topdeckfraction":0.0},{"cardtitle":"Paper Tripping","sidecode":"runner","faction":"criminal","cardpacktitle":"Data and Destiny","dpnumber":1,"cyclenumber":9,"indecks":0,"intopdecks":0,"deckfraction":0.0,"topdeckfraction":0.0},{"cardtitle":"Paper Tripping","sidecode":"runner","faction":"criminal","cardpacktitle":"D&D, post-MWL","dpnumber":2,"cyclenumber":9,"indecks":0,"intopdecks":0,"deckfraction":0.0,"topdeckfraction":0.0},{"cardtitle":"Paper Tripping","sidecode":"runner","faction":"criminal","cardpacktitle":"Kala Ghoda","dpnumber":1,"cyclenumber":10,"indecks":0,"intopdecks":0,"deckfraction":0.0,"topdeckfraction":0.0},{"cardtitle":"Paper Tripping","sidecode":"runner","faction":"criminal","cardpacktitle":"Business First","dpnumber":2,"cyclenumber":10,"indecks":0,"intopdecks":0,"deckfraction":0.0,"topdeckfraction":0.0},{"cardtitle":"Paper Tripping","sidecode":"runner","faction":"criminal","cardpacktitle":"Democracy and Dogma","dpnumber":3,"cyclenumber":10,"indecks":0,"intopdecks":0,"deckfraction":0.0,"topdeckfraction":0.0},{"cardtitle":"Paper Tripping","sidecode":"runner","faction":"criminal","cardpacktitle":"Salsette Island","dpnumber":4,"cyclenumber":10,"indecks":0,"intopdecks":0,"deckfraction":0.0,"topdeckfraction":0.0},{"cardtitle":"Paper Tripping","sidecode":"runner","faction":"criminal","cardpacktitle":"The Liberated Mind","dpnumber":5,"cyclenumber":10,"indecks":1,"intopdecks":0,"deckfraction":0.01315789483487606,"topdeckfraction":0.0},{"cardtitle":"Paper Tripping","sidecode":"runner","faction":"criminal","cardpacktitle":"Fear the Masses","dpnumber":6,"cyclenumber":10,"indecks":0,"intopdecks":0,"deckfraction":0.0,"topdeckfraction":0.0},{"cardtitle":"Paper Tripping","sidecode":"runner","faction":"criminal","cardpacktitle":"23 Seconds","dpnumber":1,"cyclenumber":11,"indecks":1,"intopdecks":0,"deckfraction":0.012658228166401386,"topdeckfraction":0.0},{"cardtitle":"Paper Tripping","sidecode":"runner","faction":"criminal","cardpacktitle":"Blood Money","dpnumber":2,"cyclenumber":11,"indecks":0,"intopdecks":0,"deckfraction":0.0,"topdeckfraction":0.0},{"cardtitle":"Paper Tripping","sidecode":"runner","faction":"criminal","cardpacktitle":"Escalation","dpnumber":3,"cyclenumber":11,"indecks":1,"intopdecks":0,"deckfraction":0.017543859779834747,"topdeckfraction":0.0},{"cardtitle":"Paper Tripping","sidecode":"runner","faction":"criminal","cardpacktitle":"Intervention","dpnumber":4,"cyclenumber":11,"indecks":3,"intopdecks":2,"deckfraction":0.019480518996715546,"topdeckfraction":0.027397260069847107},{"cardtitle":"Paper Tripping","sidecode":"runner","faction":"criminal","cardpacktitle":"Martial Law","dpnumber":5,"cyclenumber":11,"indecks":0,"intopdecks":0,"deckfraction":0.0,"topdeckfraction":0.0},{"cardtitle":"Paper Tripping","sidecode":"runner","faction":"criminal","cardpacktitle":"Quorum","dpnumber":6,"cyclenumber":11,"indecks":0,"intopdecks":0,"deckfraction":0.0,"topdeckfraction":0.0},{"cardtitle":"Paper Tripping","sidecode":"runner","faction":"criminal","cardpacktitle":"Daedalus Complex","dpnumber":1,"cyclenumber":12,"indecks":0,"intopdecks":0,"deckfraction":0.0,"topdeckfraction":0.0},{"cardtitle":"Paper Tripping","sidecode":"runner","faction":"criminal","cardpacktitle":"Station One","dpnumber":2,"cyclenumber":12,"indecks":0,"intopdecks":0,"deckfraction":0.0,"topdeckfraction":0.0},{"cardtitle":"Paper Tripping","sidecode":"runner","faction":"criminal","cardpacktitle":"Terminal Directive","dpnumber":1,"cyclenumber":13,"indecks":0,"intopdecks":0,"deckfraction":0.0,"topdeckfraction":0.0},{"cardtitle":"Paper Tripping","sidecode":"runner","faction":"criminal","cardpacktitle":"Earth's Scion","dpnumber":3,"cyclenumber":14,"indecks":0,"intopdecks":0,"deckfraction":0.0,"topdeckfraction":0.0},{"cardtitle":"Paper Tripping","sidecode":"runner","faction":"criminal","cardpacktitle":"Blood and Water","dpnumber":4,"cyclenumber":14,"indecks":0,"intopdecks":0,"deckfraction":0.0,"topdeckfraction":0.0},{"cardtitle":"Paper Tripping","sidecode":"runner","faction":"criminal","cardpacktitle":"Free Mars","dpnumber":5,"cyclenumber":14,"indecks":0,"intopdecks":0,"deckfraction":0.0,"topdeckfraction":0.0},{"cardtitle":"Paper Tripping","sidecode":"runner","faction":"criminal","cardpacktitle":"Crimson Dust","dpnumber":6,"cyclenumber":14,"indecks":0,"intopdecks":0,"deckfraction":0.0,"topdeckfraction":0.0},{"cardtitle":"Paper Tripping","sidecode":"runner","faction":"criminal","cardpacktitle":"Revised Core Set","dpnumber":1,"cyclenumber":20,"indecks":3,"intopdecks":0,"deckfraction":0.010452961549162865,"topdeckfraction":0.0},{"cardtitle":"Paper Tripping","sidecode":"runner","faction":"criminal","cardpacktitle":"Sovereign Sight","dpnumber":1,"cyclenumber":21,"indecks":0,"intopdecks":0,"deckfraction":0.0,"topdeckfraction":0.0},{"cardtitle":"Paper Tripping","sidecode":"runner","faction":"criminal","cardpacktitle":"Down the White Nile","dpnumber":2,"cyclenumber":21,"indecks":0,"intopdecks":0,"deckfraction":0.0,"topdeckfraction":0.0},{"cardtitle":"Paper Tripping","sidecode":"runner","faction":"criminal","cardpacktitle":"Council of the Crest","dpnumber":3,"cyclenumber":21,"indecks":0,"intopdecks":0,"deckfraction":0.0,"topdeckfraction":0.0},{"cardtitle":"Paper Tripping","sidecode":"runner","faction":"criminal","cardpacktitle":"The Devil and the Dragon","dpnumber":4,"cyclenumber":21,"indecks":0,"intopdecks":0,"deckfraction":0.0,"topdeckfraction":0.0},{"cardtitle":"Paper Tripping","sidecode":"runner","faction":"criminal","cardpacktitle":"Whispers in Nalubaale","dpnumber":5,"cyclenumber":21,"indecks":0,"intopdecks":0,"deckfraction":0.0,"topdeckfraction":0.0},{"cardtitle":"Paper Tripping","sidecode":"runner","faction":"criminal","cardpacktitle":"Kampala Ascendent","dpnumber":6,"cyclenumber":21,"indecks":2,"intopdecks":1,"deckfraction":0.01600000075995922,"topdeckfraction":0.016393441706895828},{"cardtitle":"Paper Tripping","sidecode":"runner","faction":"criminal","cardpacktitle":"Reign and Reverie","dpnumber":1,"cyclenumber":22,"indecks":1,"intopdecks":0,"deckfraction":0.0034129691775888205,"topdeckfraction":0.0},{"cardtitle":"Paper Tripping","sidecode":"runner","faction":"criminal","cardpacktitle":"R&R MWL 2.2","dpnumber":2,"cyclenumber":22,"indecks":0,"intopdecks":0,"deckfraction":0.0,"topdeckfraction":0.0},{"cardtitle":"Paper Tripping","sidecode":"runner","faction":"criminal","cardpacktitle":"Magnum Opus","dpnumber":1,"cyclenumber":23,"indecks":0,"intopdecks":0,"deckfraction":0.0,"topdeckfraction":0.0}],"top":[{"cardtitle":"Liza Talking Thunder: Prominent Legislator","sidecode":"runner","faction":"criminal","cardpacktitle":"Reign and Reverie","dpnumber":1,"cyclenumber":22,"indecks":1,"intopdecks":-1,"deckfraction":0.03703703731298447,"topdeckfraction":-1.0}],"combos":[{"title":"Spear Phishing","pack":"Terminal Directive","faction":"criminal","score":14},{"title":"Mongoose","pack":"Kala Ghoda","faction":"criminal","score":9},{"title":"Fisk Investment Seminar","pack":"The Universe of Tomorrow","faction":"criminal","score":5},{"title":"Film Critic","pack":"Old Hollywood","faction":"shaper","score":5},{"title":"Dorm Computer","pack":"Breaker Bay","faction":"criminal","score":4},{"title":"Diversion of Funds","pack":"Kampala Ascendent","faction":"criminal","score":3},{"title":"Legwork","pack":"Honor and Profit","faction":"criminal","score":3},{"title":"Aumakua","pack":"Crimson Dust","faction":"criminal","score":2},{"title":"Sure Gamble","pack":"Revised Core Set","faction":"neutral","score":2},{"title":"Amina","pack":"Kampala Ascendent","faction":"criminal","score":1}],"decks":[{"count":0,"dpnumber":1,"cyclenumber":23,"dptitle":"Magnum Opus","deckLinks":[]},{"count":0,"dpnumber":2,"cyclenumber":22,"dptitle":"R&R MWL 2.2","deckLinks":[]},{"count":1,"dpnumber":1,"cyclenumber":22,"dptitle":"Reign and Reverie","deckLinks":["<a href=\"https://netrunnerdb.com/en/decklist/51631\" rel=\"nofollow\" target=\"_blank\">Nexus Liza</a> by <em>Redino987</em> (#16 / 46 at Compleat Strategist - New York City Regionals)"]},{"count":2,"dpnumber":6,"cyclenumber":21,"dptitle":"Kampala Ascendent","deckLinks":["<a href=\"https://netrunnerdb.com/en/decklist/50800\" rel=\"nofollow\" target=\"_blank\">Incubator Freedom</a> by <em>PureFlight</em> (#13 / 44 at Chicago Regionals)","<a href=\"https://netrunnerdb.com/en/decklist/51365\" rel=\"nofollow\" target=\"_blank\">Smooth Criminal (Malaysian GNK Q1 2018)</a> by <em>supercatfish</em> (#4 / 6 at GNK Q1 2018)"]},{"count":0,"dpnumber":5,"cyclenumber":21,"dptitle":"Whispers in Nalubaale","deckLinks":[]},{"count":0,"dpnumber":4,"cyclenumber":21,"dptitle":"The Devil and the Dragon","deckLinks":[]},{"count":0,"dpnumber":3,"cyclenumber":21,"dptitle":"Council of the Crest","deckLinks":[]},{"count":0,"dpnumber":2,"cyclenumber":21,"dptitle":"Down the White Nile","deckLinks":[]},{"count":0,"dpnumber":1,"cyclenumber":21,"dptitle":"Sovereign Sight","deckLinks":[]},{"count":3,"dpnumber":1,"cyclenumber":20,"dptitle":"Revised Core Set","deckLinks":["<a href=\"https://netrunnerdb.com/en/decklist/46501\" rel=\"nofollow\" target=\"_blank\">Quetzal Budapest</a> by <em>shadowhawk</em> (#8 / 22 at Android Netrunner Nationals 2017)","<a href=\"https://netrunnerdb.com/en/decklist/47112\" rel=\"nofollow\" target=\"_blank\">The Kenagerie</a> by <em>Cuacuani</em> (#12 / 12 at Cambridge GNK)","<a href=\"https://netrunnerdb.com/en/decklist/47112\" rel=\"nofollow\" target=\"_blank\">The Kenagerie</a> by <em>Cuacuani</em> (#12 / 12 at Cambridge GNK)"]},{"count":0,"dpnumber":6,"cyclenumber":14,"dptitle":"Crimson Dust","deckLinks":[]},{"count":0,"dpnumber":5,"cyclenumber":14,"dptitle":"Free Mars","deckLinks":[]},{"count":0,"dpnumber":4,"cyclenumber":14,"dptitle":"Blood and Water","deckLinks":[]},{"count":0,"dpnumber":3,"cyclenumber":14,"dptitle":"Earth's Scion","deckLinks":[]},{"count":0,"dpnumber":1,"cyclenumber":13,"dptitle":"Terminal Directive","deckLinks":[]},{"count":0,"dpnumber":2,"cyclenumber":12,"dptitle":"Station One","deckLinks":[]},{"count":0,"dpnumber":1,"cyclenumber":12,"dptitle":"Daedalus Complex","deckLinks":[]},{"count":0,"dpnumber":6,"cyclenumber":11,"dptitle":"Quorum","deckLinks":[]},{"count":0,"dpnumber":5,"cyclenumber":11,"dptitle":"Martial Law","deckLinks":[]},{"count":3,"dpnumber":4,"cyclenumber":11,"dptitle":"Intervention","deckLinks":["<a href=\"https://netrunnerdb.com/en/deck/view/799538\" rel=\"nofollow\" target=\"_blank\">Charity Gift Ken</a> by <em>deaglesuk</em> (#7 / 32 at Charity Gift II)","<a href=\"https://netrunnerdb.com/en/decklist/40876\" rel=\"nofollow\" target=\"_blank\">Charity Gift 2016 - Gabe Deck</a> by <em>Critical Joe</em> (#9 / 32 at Charity Gift II)","<a href=\"https://netrunnerdb.com/en/decklist/39421\" rel=\"nofollow\" target=\"_blank\">Andy: N.A. Confidential v1.12</a> by <em>saracenus</em> (#4 / 8 at The Portland Game Store: Store Championship)"]},{"count":1,"dpnumber":3,"cyclenumber":11,"dptitle":"Escalation","deckLinks":["<a href=\"https://netrunnerdb.com/en/deck/view/801990\" rel=\"nofollow\" target=\"_blank\">Gang Leela Go Faust</a> by <em>aquir</em> (#8 / 12 at Hungarian third league, tournament #1)"]},{"count":0,"dpnumber":2,"cyclenumber":11,"dptitle":"Blood Money","deckLinks":[]},{"count":1,"dpnumber":1,"cyclenumber":11,"dptitle":"23 Seconds","deckLinks":["<a href=\"http://www.acoo.net/deck/19355\" rel=\"nofollow\" target=\"_blank\">Sandtag</a> by <em>Barry Smith</em> (#60 / 87 at Reading Regional 2016)"]},{"count":0,"dpnumber":6,"cyclenumber":10,"dptitle":"Fear the Masses","deckLinks":[]},{"count":1,"dpnumber":5,"cyclenumber":10,"dptitle":"The Liberated Mind","deckLinks":["<a href=\"http://www.acoo.net/deck/18652\" rel=\"nofollow\" target=\"_blank\">Turning Wheel Andy</a> by <em>Oskar Christensson</em> (#23 / 25 at Stockholm Regional)"]},{"count":0,"dpnumber":4,"cyclenumber":10,"dptitle":"Salsette Island","deckLinks":[]},{"count":0,"dpnumber":3,"cyclenumber":10,"dptitle":"Democracy and Dogma","deckLinks":[]},{"count":0,"dpnumber":2,"cyclenumber":10,"dptitle":"Business First","deckLinks":[]},{"count":0,"dpnumber":1,"cyclenumber":10,"dptitle":"Kala Ghoda","deckLinks":[]},{"count":0,"dpnumber":2,"cyclenumber":9,"dptitle":"D&D, post-MWL","deckLinks":[]},{"count":0,"dpnumber":1,"cyclenumber":9,"dptitle":"Data and Destiny","deckLinks":[]},{"count":0,"dpnumber":6,"cyclenumber":8,"dptitle":"The Universe of Tomorrow","deckLinks":[]},{"count":0,"dpnumber":5,"cyclenumber":8,"dptitle":"Old Hollywood","deckLinks":[]},{"count":0,"dpnumber":4,"cyclenumber":8,"dptitle":"The Underway","deckLinks":[]},{"count":0,"dpnumber":3,"cyclenumber":8,"dptitle":"Chrome City","deckLinks":[]},{"count":0,"dpnumber":2,"cyclenumber":8,"dptitle":"Breaker Bay","deckLinks":[]},{"count":0,"dpnumber":1,"cyclenumber":8,"dptitle":"The Valley","deckLinks":[]},{"count":0,"dpnumber":1,"cyclenumber":7,"dptitle":"Order and Chaos","deckLinks":[]},{"count":1,"dpnumber":6,"cyclenumber":6,"dptitle":"The Source","deckLinks":["<a href=\"http://www.acoo.net/deck/6780\" rel=\"nofollow\" target=\"_blank\">Logos Leela</a> by <em>Tobin Lopes</em> (#2 / 22 at The Wizard's Chest 2015 Store Championship)"]},{"count":0,"dpnumber":5,"cyclenumber":6,"dptitle":"All That Remains","deckLinks":[]},{"count":0,"dpnumber":4,"cyclenumber":6,"dptitle":"Up and Over","deckLinks":[]}]}