{"title":"Daredevil","code":"12066","overTime":[{"cardtitle":"Daredevil","sidecode":"runner","faction":"shaper","cardpacktitle":"Blood and Water","dpnumber":4,"cyclenumber":14,"indecks":4,"intopdecks":3,"deckfraction":0.042553190141916275,"topdeckfraction":0.06666667014360428},{"cardtitle":"Daredevil","sidecode":"runner","faction":"shaper","cardpacktitle":"Free Mars","dpnumber":5,"cyclenumber":14,"indecks":10,"intopdecks":6,"deckfraction":0.06329113990068436,"topdeckfraction":0.07228915393352509},{"cardtitle":"Daredevil","sidecode":"runner","faction":"shaper","cardpacktitle":"Crimson Dust","dpnumber":6,"cyclenumber":14,"indecks":3,"intopdecks":0,"deckfraction":0.04054053872823715,"topdeckfraction":0.0},{"cardtitle":"Daredevil","sidecode":"runner","faction":"shaper","cardpacktitle":"Revised Core Set","dpnumber":1,"cyclenumber":20,"indecks":11,"intopdecks":3,"deckfraction":0.038327526301145554,"topdeckfraction":0.02054794505238533},{"cardtitle":"Daredevil","sidecode":"runner","faction":"shaper","cardpacktitle":"Sovereign Sight","dpnumber":1,"cyclenumber":21,"indecks":3,"intopdecks":1,"deckfraction":0.034090910106897354,"topdeckfraction":0.019607843831181526},{"cardtitle":"Daredevil","sidecode":"runner","faction":"shaper","cardpacktitle":"Down the White Nile","dpnumber":2,"cyclenumber":21,"indecks":2,"intopdecks":1,"deckfraction":0.010869565419852734,"topdeckfraction":0.009900989942252636},{"cardtitle":"Daredevil","sidecode":"runner","faction":"shaper","cardpacktitle":"Council of the Crest","dpnumber":3,"cyclenumber":21,"indecks":3,"intopdecks":1,"deckfraction":0.01923076994717121,"topdeckfraction":0.013333333656191826},{"cardtitle":"Daredevil","sidecode":"runner","faction":"shaper","cardpacktitle":"The Devil and the Dragon","dpnumber":4,"cyclenumber":21,"indecks":1,"intopdecks":0,"deckfraction":0.0833333358168602,"topdeckfraction":0.0},{"cardtitle":"Daredevil","sidecode":"runner","faction":"shaper","cardpacktitle":"Whispers in Nalubaale","dpnumber":5,"cyclenumber":21,"indecks":0,"intopdecks":0,"deckfraction":0.0,"topdeckfraction":0.0},{"cardtitle":"Daredevil","sidecode":"runner","faction":"shaper","cardpacktitle":"Kampala Ascendent","dpnumber":6,"cyclenumber":21,"indecks":0,"intopdecks":0,"deckfraction":0.0,"topdeckfraction":0.0},{"cardtitle":"Daredevil","sidecode":"runner","faction":"shaper","cardpacktitle":"Reign and Reverie","dpnumber":1,"cyclenumber":22,"indecks":2,"intopdecks":1,"deckfraction":0.007017544005066156,"topdeckfraction":0.007092198356986046},{"cardtitle":"Daredevil","sidecode":"runner","faction":"shaper","cardpacktitle":"R&R MWL 2.2","dpnumber":2,"cyclenumber":22,"indecks":1,"intopdecks":1,"deckfraction":0.004950494971126318,"topdeckfraction":0.009433962404727936},{"cardtitle":"Daredevil","sidecode":"runner","faction":"shaper","cardpacktitle":"Magnum Opus","dpnumber":1,"cyclenumber":23,"indecks":1,"intopdecks":0,"deckfraction":0.00800000037997961,"topdeckfraction":0.0},{"cardtitle":"Daredevil","sidecode":"runner","faction":"shaper","cardpacktitle":"System Core 2019","dpnumber":1,"cyclenumber":25,"indecks":0,"intopdecks":0,"deckfraction":0.0,"topdeckfraction":0.0},{"cardtitle":"Daredevil","sidecode":"runner","faction":"shaper","cardpacktitle":"Downfall","dpnumber":1,"cyclenumber":26,"indecks":2,"intopdecks":1,"deckfraction":0.008368200622498989,"topdeckfraction":0.009803921915590763},{"cardtitle":"Daredevil","sidecode":"runner","faction":"shaper","cardpacktitle":"Downfall MWL 3.2","dpnumber":2,"cyclenumber":26,"indecks":2,"intopdecks":1,"deckfraction":0.015748031437397003,"topdeckfraction":0.016393441706895828}],"top":[{"cardtitle":"Kabonesa Wu: Netspace Thrillseeker","sidecode":"runner","faction":"shaper","cardpacktitle":"Down the White Nile","dpnumber":2,"cyclenumber":21,"indecks":4,"intopdecks":-1,"deckfraction":0.17391304671764374,"topdeckfraction":-1.0}],"combos":[{"title":"Au Revoir","pack":"The Source","faction":"criminal","score":159},{"title":"Beth Kilrain-Chang","pack":"Blood Money","faction":"shaper","score":56},{"title":"Self-modifying Code","pack":"Creation and Control","faction":"shaper","score":49},{"title":"Cyberdelia","pack":"Sovereign Sight","faction":"shaper","score":41},{"title":"Cold Read","pack":"Martial Law","faction":"shaper","score":33},{"title":"Clot","pack":"The Valley","faction":"anarch","score":31},{"title":"Ankusa","pack":"Fear the Masses","faction":"shaper","score":29},{"title":"Film Critic","pack":"Old Hollywood","faction":"shaper","score":28},{"title":"Reshape","pack":"Crimson Dust","faction":"shaper","score":25},{"title":"NetChip","pack":"Business First","faction":"shaper","score":20}],"decks":[{"count":2,"dpnumber":2,"cyclenumber":26,"dptitle":"Downfall MWL 3.2","deckLinks":["<a href=\"https://netrunnerdb.com/en/decklist/55627\" rel=\"nofollow\" target=\"_blank\">Free MTI (2nd place NISEI Jinteki.net standard 5W 3L)</a> by <em>mo0man</em> (#2 / 16 at Nisei Standard Top 16)","<a href=\"https://netrunnerdb.com/en/decklist/55658\" rel=\"nofollow\" target=\"_blank\">Wu Revoir (Technically Top Cut - Nisei Standard)</a> by <em>EnderA</em> (#16 / 16 at Nisei Standard Top 16)"]},{"count":2,"dpnumber":1,"cyclenumber":26,"dptitle":"Downfall","deckLinks":["<a href=\"https://netrunnerdb.com/en/decklist/55482\" rel=\"nofollow\" target=\"_blank\">See Wu, Net Cowboy</a> by <em>Dirjel</em> (#1 / 5 at Phoenix Store Championship)","<a href=\"https://netrunnerdb.com/en/decklist/55565\" rel=\"nofollow\" target=\"_blank\">Wu Revoir, Mti</a> by <em>swabl</em> (#9 / 10 at Reading May GNK)"]},{"count":0,"dpnumber":1,"cyclenumber":25,"dptitle":"System Core 2019","deckLinks":[]},{"count":1,"dpnumber":1,"cyclenumber":23,"dptitle":"Magnum Opus","deckLinks":["<a href=\"https://netrunnerdb.com/en/decklist/53557\" rel=\"nofollow\" target=\"_blank\">Big Rig Iain Stirling (ID Swap)</a> by <em>Manta</em> (#6 / 11 at Louisville Gameshop - 2018 Q3 Kit (1 of 2))"]},{"count":1,"dpnumber":2,"cyclenumber":22,"dptitle":"R&R MWL 2.2","deckLinks":["<a href=\"https://netrunnerdb.com/en/decklist/52472\" rel=\"nofollow\" target=\"_blank\">Lean and Mean: Stealth Kabonesa (29th @ Worlds)</a> by <em>allofthemarbles</em> (#29 / 403 at Magnum Opus (Worlds 2018))"]},{"count":2,"dpnumber":1,"cyclenumber":22,"dptitle":"Reign and Reverie","deckLinks":["<a href=\"https://netrunnerdb.com/en/decklist/52117\" rel=\"nofollow\" target=\"_blank\">Engolokit</a> by <em>b3ar</em> (#2 / 7 at Netrunner LCG Turnier Abend)","<a href=\"https://netrunnerdb.com/en/decklist/49299\" rel=\"nofollow\" target=\"_blank\">Swipsy-Swapsies (3-1 Kzoo SC)</a> by <em>PureFlight</em> (#20 / 33 at Regionals Stockholm, Sweden 2018)"]},{"count":0,"dpnumber":6,"cyclenumber":21,"dptitle":"Kampala Ascendent","deckLinks":[]},{"count":0,"dpnumber":5,"cyclenumber":21,"dptitle":"Whispers in Nalubaale","deckLinks":[]},{"count":1,"dpnumber":4,"cyclenumber":21,"dptitle":"The Devil and the Dragon","deckLinks":["<a href=\"https://netrunnerdb.com/en/decklist/48967\" rel=\"nofollow\" target=\"_blank\">Wubicon - Undefeated Colorado SC - 2nd Place</a> by <em>mathandlove</em> (#4 / 8 at Rockford GNK - April 2018)"]},{"count":3,"dpnumber":3,"cyclenumber":21,"dptitle":"Council of the Crest","deckLinks":["<a href=\"https://netrunnerdb.com/en/decklist/48967\" rel=\"nofollow\" target=\"_blank\">Wubicon - Undefeated Colorado SC - 2nd Place</a> by <em>mathandlove</em> (#4 / 8 at Rockford GNK - April 2018)","<a href=\"https://netrunnerdb.com/en/decklist/49299\" rel=\"nofollow\" target=\"_blank\">Swipsy-Swapsies (3-1 Kzoo SC)</a> by <em>PureFlight</em> (#20 / 33 at Regionals Stockholm, Sweden 2018)","<a href=\"https://netrunnerdb.com/en/decklist/49299\" rel=\"nofollow\" target=\"_blank\">Swipsy-Swapsies (3-1 Kzoo SC)</a> by <em>PureFlight</em> (#20 / 33 at Regionals Stockholm, Sweden 2018)"]},{"count":2,"dpnumber":2,"cyclenumber":21,"dptitle":"Down the White Nile","deckLinks":["<a href=\"https://netrunnerdb.com/en/decklist/48967\" rel=\"nofollow\" target=\"_blank\">Wubicon - Undefeated Colorado SC - 2nd Place</a> by <em>mathandlove</em> (#4 / 8 at Rockford GNK - April 2018)","<a href=\"https://netrunnerdb.com/en/decklist/46467\" rel=\"nofollow\" target=\"_blank\">Chaos Theory, Code Savant</a> by <em>severininfurs</em> (#6 / 8 at Common Ground Games - Store Championship)"]},{"count":3,"dpnumber":1,"cyclenumber":21,"dptitle":"Sovereign Sight","deckLinks":["<a href=\"https://netrunnerdb.com/en/decklist/47683\" rel=\"nofollow\" target=\"_blank\">CyberDevil 2.0</a> by <em>Joseki</em> (#3 / 16 at Gamescape SF Store Championship)","<a href=\"https://netrunnerdb.com/en/decklist/47505\" rel=\"nofollow\" target=\"_blank\">CyberDevil</a> by <em>Joseki</em> (#1 / 3 at Eudo 3rd December GNK)","<a href=\"https://netrunnerdb.com/en/decklist/47975\" rel=\"nofollow\" target=\"_blank\">Inverse Kit</a> by <em>wigglestick</em> (#4 / 8 at Spielbound GNK)"]},{"count":11,"dpnumber":1,"cyclenumber":20,"dptitle":"Revised Core Set","deckLinks":["<a href=\"https://netrunnerdb.com/en/decklist/45822\" rel=\"nofollow\" target=\"_blank\">Smoke Post Rotation</a> by <em>MazeBerlin</em> (#1 / 34 at CZ/SK Nationals 2017, Bratislava (SK))","<a href=\"https://netrunnerdb.com/en/decklist/46714\" rel=\"nofollow\" target=\"_blank\">Daredevil Smoke - 1st at Hungarian Nationals 2017</a> by <em>percomis</em> (#1 / 22 at Android Netrunner Nationals 2017)","<a href=\"https://netrunnerdb.com/en/decklist/45822\" rel=\"nofollow\" target=\"_blank\">Smoke Post Rotation</a> by <em>MazeBerlin</em> (#1 / 34 at CZ/SK Nationals 2017, Bratislava (SK))","<a href=\"https://netrunnerdb.com/en/decklist/46415\" rel=\"nofollow\" target=\"_blank\">Thrillseeker (2-1 Cambridge GNK)</a> by <em>Countzer0</em> (#3 / 15 at Cambridge GNK)","<a href=\"https://netrunnerdb.com/en/decklist/46329\" rel=\"nofollow\" target=\"_blank\">Good stuff Smoke (Nothing new here)</a> by <em>HoneyBadger</em> (#3 / 7 at Netrunner Post-rotation Tournament)","<a href=\"https://netrunnerdb.com/en/decklist/45772\" rel=\"nofollow\" target=\"_blank\">Speedy Smoke (Revised Core compatible)</a> by <em>szutek</em> (#3 / 7 at gnk q3 2017)","<a href=\"https://netrunnerdb.com/en/decklist/47647\" rel=\"nofollow\" target=\"_blank\">Daredevil Ken</a> by <em>Countzer0</em> (#23 / 43 at Reading SC - Eclectic Games)","<a href=\"https://netrunnerdb.com/en/decklist/45984\" rel=\"nofollow\" target=\"_blank\">Mindchanger</a> by <em>mcg</em> (#5 / 8 at Fan Boy Three Netrunner Games Night Kit - Rotation)","<a href=\"https://netrunnerdb.com/en/decklist/46628\" rel=\"nofollow\" target=\"_blank\">CT Test v23</a> by <em>Ulkrond</em> (#200 / 233 at [2017 WORLDS CHAMPIONSHIP])","<a href=\"https://netrunnerdb.com/en/decklist/47112\" rel=\"nofollow\" target=\"_blank\">The Kenagerie</a> by <em>Cuacuani</em> (#12 / 12 at Cambridge GNK)","..."]},{"count":3,"dpnumber":6,"cyclenumber":14,"dptitle":"Crimson Dust","deckLinks":["<a href=\"https://netrunnerdb.com/en/decklist/46900\" rel=\"nofollow\" target=\"_blank\">Criminal: Khan (Gaming vs Cancer 2017)</a> by <em>protolich</em> (#17 / 34 at GvsC Android: Netrunner 2017)","<a href=\"https://netrunnerdb.com/en/deck/view/996898\" rel=\"nofollow\" target=\"_blank\">My Version of $5 Pawn (v0.04)</a> by <em>seeds34</em> (#65 / 85 at UK Nationals 2017)","<a href=\"https://netrunnerdb.com/en/decklist/45050\" rel=\"nofollow\" target=\"_blank\">Smoke</a> by <em>blindidiotgod</em> (#36 / 44 at Australian Netrunner Nationals - Sydney)"]},{"count":10,"dpnumber":5,"cyclenumber":14,"dptitle":"Free Mars","deckLinks":["<a href=\"https://netrunnerdb.com/en/decklist/44885\" rel=\"nofollow\" target=\"_blank\">ReaverShop: Revisited</a> by <em>stCarolas</em> (#1 / 11 at Moscow GNK 2017-08-20)","<a href=\"https://netrunnerdb.com/en/decklist/44524\" rel=\"nofollow\" target=\"_blank\">Grape Juice FM (1st Store Champs, Edmonton Alberta)</a> by <em>CaKnuckleguy</em> (#1 / 9 at Netrunner 2016* Champion Kit Tournament)","<a href=\"https://netrunnerdb.com/en/decklist/44781\" rel=\"nofollow\" target=\"_blank\">CodeMarvelous's FiverShop (1st place GNK)</a> by <em>osclate</em> (#1 / 8 at Q2 Game Night Kit at Days of Knights)","<a href=\"https://netrunnerdb.com/en/decklist/44644\" rel=\"nofollow\" target=\"_blank\">Daring Darling</a> by <em>Necro</em> (#3 / 17 at Third Hungarian League - Top 4 Finals)","<a href=\"https://netrunnerdb.com/en/decklist/44765\" rel=\"nofollow\" target=\"_blank\">InversifiKitter - 08/14/17 GNK</a> by <em>Ino209</em> (#2 / 8 at Q2 Game Night Kit at Days of Knights)","<a href=\"https://netrunnerdb.com/en/deck/view/972720\" rel=\"nofollow\" target=\"_blank\">Destino</a> by <em>funeral0polis</em> (#2 / 7 at The Comic Hunter 2017 Q2 Tournament Kit)","<a href=\"https://netrunnerdb.com/en/decklist/44546\" rel=\"nofollow\" target=\"_blank\">BBK</a> by <em>acrowe</em> (#4 / 9 at Netrunner 2016* Champion Kit Tournament)","<a href=\"https://netrunnerdb.com/en/decklist/44566\" rel=\"nofollow\" target=\"_blank\">FiverShop</a> by <em>CodeMarvelous</em> (#41 / 67 at German National Championship)","<a href=\"https://netrunnerdb.com/en/decklist/44757\" rel=\"nofollow\" target=\"_blank\">Silence Kit (Dutch Nationals)</a> by <em>nismorack</em> (#41 / 56 at Dutch Netrunner Nationals 2017)","<a href=\"https://netrunnerdb.com/en/decklist/45087\" rel=\"nofollow\" target=\"_blank\">Silence Kit v1.5</a> by <em>PeterPan</em> (#63 / 67 at German National Championship)"]},{"count":4,"dpnumber":4,"cyclenumber":14,"dptitle":"Blood and Water","deckLinks":["<a href=\"https://netrunnerdb.com/en/decklist/44282\" rel=\"nofollow\" target=\"_blank\">Grape Juice - 2nd Place Colorado Regionals</a> by <em>Sanjay</em> (#2 / 29 at Colorado 2017 Regional Championship)","<a href=\"https://netrunnerdb.com/en/decklist/44160\" rel=\"nofollow\" target=\"_blank\">InversifiKitter - 3rd place at ANRPC Charity Tournament</a> by <em>Ino209</em> (#3 / 15 at ANRPC Child's Play Charity Netrunner Tournament)","<a href=\"https://netrunnerdb.com/en/decklist/44489\" rel=\"nofollow\" target=\"_blank\">Daredevil Kit</a> by <em>Rezalbyks</em> (#3 / 13 at ANR Q3 GNK 2017 @ The Attic)","<a href=\"https://netrunnerdb.com/en/decklist/44159\" rel=\"nofollow\" target=\"_blank\">Smoke</a> by <em>blindidiotgod</em> (#9 / 22 at NSW Netrunner Regionals + Second Day Event)"]}]}